{"files":{"pages\\nav.vue":{"frameworks":["vuetify","pg.insight.events","@vue/devtools","pg.vue.tree.painter","@nuxt/devtools","@unocss/preset-icons","pg.css.grid","@pinegrow/nuxt-module","project","pg.image.overlay","nuxt","pg.code-validator","vue","pg.project.items","app_designer","pg.asset.manager","pg.html"]},"pages\\login.vue":{"frameworks":["vuetify","@vue/devtools","@nuxt/devtools","@unocss/preset-icons","@pinegrow/nuxt-module","nuxt","vue","app_designer","project","pg.insight.events","pg.vue.tree.painter","pg.css.grid","pg.image.overlay","pg.code-validator","pg.project.items","pg.asset.manager","pg.html"]},"pages\\index.vue":{"frameworks":["vuetify","@vue/devtools","@nuxt/devtools","@unocss/preset-icons","@pinegrow/nuxt-module","nuxt","vue","app_designer","project","pg.insight.events","pg.vue.tree.painter","pg.css.grid","pg.image.overlay","pg.code-validator","pg.project.items","pg.asset.manager","pg.html"]}},"template_framework_id":"vue","open-pages":["pages/index.vue","pages/nav.vue","pages/login.vue"],"recent-classes":["bg-blue"],"breakpoints":[],"frameworks":["vuetify","pg.insight.events","@vue/devtools","pg.vue.tree.painter","@nuxt/devtools","@unocss/preset-icons","pg.css.grid","@pinegrow/nuxt-module","project","pg.image.overlay","nuxt","pg.code-validator","vue","pg.project.items","app_designer","pg.asset.manager","pg.html"],"urls":{"pages/nav.vue":{"open-page-views":[{"w":1024,"h":0}]},"pages/login.vue":{"open-page-views":[{"w":1024,"h":0}]},"pages/index.vue":{"open-page-views":[{"w":1024,"h":0}]}}}